fraxtionz.py
fraxtionz-2.4.1.post2.dist-info/METADATA
fraxtionz-2.4.1.post2.dist-info/WHEEL
fraxtionz-2.4.1.post2.dist-info/top_level.txt
fraxtionz-2.4.1.post2.dist-info/RECORD
