Metadata-Version: 2.1
Name: fraxtionz
Version: 2.4.1.post2
Summary: UNKNOWN
Home-page: UNKNOWN
Author: Elia Toselli
Author-email: elia.toselli3@gmail.com
License: GPL
Platform: UNKNOWN
